download_twitter_resources/__init__.py
download_twitter_resources/__main__.py
download_twitter_resources/async_executor.py
download_twitter_resources/auth.py
download_twitter_resources/downloader.py
download_twitter_resources/exceptions.py
download_twitter_resources/unittest.py
download_twitter_resources-0.2.3.dist-info/METADATA
download_twitter_resources-0.2.3.dist-info/WHEEL
download_twitter_resources-0.2.3.dist-info/entry_points.txt
download_twitter_resources-0.2.3.dist-info/top_level.txt
download_twitter_resources-0.2.3.dist-info/RECORD
