Metadata-Version: 2.1
Name: download-twitter-resources
Version: 0.2.3
Summary: Download tweet images and videos
Home-page: https://github.com/weaming/download-twitter-resources
Author: weaming
Author-email: garden.yuen@gmail.com
License: UNKNOWN
Project-URL: Source, https://github.com/weaming/download-twitter-resources
Project-URL: Bug Reports, https://github.com/weaming/download-twitter-resources
Keywords: math
Platform: UNKNOWN
Requires-Dist: python-dateutil (>=2.7.3)
Requires-Dist: requests (>=2.20.0)
Requires-Dist: aiohttp (>=3.4.4)
Requires-Dist: rauth (==0.7.3)
